oocana_python_executor-0.16.16.dist-info/METADATA
oocana_python_executor-0.16.16.dist-info/WHEEL
oocana_python_executor-0.16.16.dist-info/entry_points.txt
python_executor/__init__.py
python_executor/block.py
python_executor/context.py
python_executor/credential.py
python_executor/data.py
python_executor/executor.py
python_executor/hook.py
python_executor/logger.py
python_executor/matplot/matplotlib_oomol/__init__.py
python_executor/matplot/matplotlib_oomol/oomol.py
python_executor/matplot/oomol_matplot_helper.py
python_executor/secret.py
python_executor/service.py
python_executor/topic.py
python_executor/utils.py
oocana_python_executor-0.16.16.dist-info/RECORD
