Metadata-Version: 2.1
Name: oocana-python-executor
Version: 0.16.16
Summary: a client subscribe mqtt topic to execute oocana's block
Author-Email: l1shen <lishen1635@gmail.com>, yleaf <11785335+leavesster@users.noreply.github.com>
License: MIT
Requires-Python: >=3.9
Requires-Dist: oocana
Provides-Extra: debug
Requires-Dist: debugpy; extra == "debug"
